__init__.py
clear_outside_apy.py
clear_outside_apy-1.0.0.dist-info/LICENSE
clear_outside_apy-1.0.0.dist-info/METADATA
clear_outside_apy-1.0.0.dist-info/WHEEL
clear_outside_apy-1.0.0.dist-info/top_level.txt
clear_outside_apy-1.0.0.dist-info/RECORD
